README.rst
setup.cfg
setup.py
django_crowd_auth/__init__.py
django_crowd_auth/backends.py
django_crowd_auth/client.py
django_crowd_auth/middlewares.py
django_crowd_auth/user.py
django_crowd_auth.egg-info/PKG-INFO
django_crowd_auth.egg-info/SOURCES.txt
django_crowd_auth.egg-info/dependency_links.txt
django_crowd_auth.egg-info/requires.txt
django_crowd_auth.egg-info/top_level.txt
django_crowd_auth/management/__init__.py
django_crowd_auth/management/commands/__init__.py
django_crowd_auth/management/commands/sync_crowd.py