Metadata-Version: 1.1
Name: django-crowd-auth
Version: 0.2.0
Summary: UNKNOWN
Home-page: UNKNOWN
Author: Philippe Muller
Author-email: philippe.muller@gmail.com
License: UNKNOWN
Platform: UNKNOWN
Classifier: Programming Language :: Python :: 3.5
